{"point_location": [4.660554885864258, 6.541022777557373, 2.3350167274475098], "point_uuid": "31", "views": [{"camera_uuid": "4c0d1c450c3c414c8e903e49190ad5f3", "point_uuid": "8", "nonfixated_pixel_x": 123, "nonfixated_pixel_y": 280, "view_id": 0}, {"camera_uuid": "1eea2dc63a804bb98c4433aaf5355d4d", "point_uuid": "8", "nonfixated_pixel_x": 169, "nonfixated_pixel_y": 278, "view_id": 4}, {"camera_uuid": "4c0d1c450c3c414c8e903e49190ad5f3", "point_uuid": "9", "nonfixated_pixel_x": 387, "nonfixated_pixel_y": 274, "view_id": 0}, {"camera_uuid": "1eea2dc63a804bb98c4433aaf5355d4d", "point_uuid": "9", "nonfixated_pixel_x": 376, "nonfixated_pixel_y": 263, "view_id": 2}, {"camera_uuid": "1eea2dc63a804bb98c4433aaf5355d4d", "point_uuid": "10", "nonfixated_pixel_x": 488, "nonfixated_pixel_y": 145, "view_id": 2}, {"camera_uuid": "1eea2dc63a804bb98c4433aaf5355d4d", "point_uuid": "11", "nonfixated_pixel_x": 201, "nonfixated_pixel_y": 133, "view_id": 0}, {"camera_uuid": "4c0d1c450c3c414c8e903e49190ad5f3", "point_uuid": "11", "nonfixated_pixel_x": 168, "nonfixated_pixel_y": 105, "view_id": 2}, {"camera_uuid": "b2b91e26cb9a4190a097925afea72a8a", "point_uuid": "11", "nonfixated_pixel_x": 216, "nonfixated_pixel_y": 88, "view_id": 3}, {"camera_uuid": "4c0d1c450c3c414c8e903e49190ad5f3", "point_uuid": "12", "nonfixated_pixel_x": 99, "nonfixated_pixel_y": 260, "view_id": 1}, {"camera_uuid": "b2b91e26cb9a4190a097925afea72a8a", "point_uuid": "13", "nonfixated_pixel_x": 332, "nonfixated_pixel_y": 154, "view_id": 0}, {"camera_uuid": "4c0d1c450c3c414c8e903e49190ad5f3", "point_uuid": "13", "nonfixated_pixel_x": 240, "nonfixated_pixel_y": 157, "view_id": 2}, {"camera_uuid": "1eea2dc63a804bb98c4433aaf5355d4d", "point_uuid": "13", "nonfixated_pixel_x": 269, "nonfixated_pixel_y": 178, "view_id": 3}, {"camera_uuid": "4c0d1c450c3c414c8e903e49190ad5f3", "point_uuid": "14", "nonfixated_pixel_x": 163, "nonfixated_pixel_y": 98, "view_id": 0}, {"camera_uuid": "1eea2dc63a804bb98c4433aaf5355d4d", "point_uuid": "14", "nonfixated_pixel_x": 201, "nonfixated_pixel_y": 129, "view_id": 1}, {"camera_uuid": "b2b91e26cb9a4190a097925afea72a8a", "point_uuid": "14", "nonfixated_pixel_x": 222, "nonfixated_pixel_y": 78, "view_id": 3}, {"camera_uuid": "029e8bd017804e6aba4c5206f049bf52", "point_uuid": "16", "nonfixated_pixel_x": 179, "nonfixated_pixel_y": 176, "view_id": 2}, {"camera_uuid": "4941e1733c7d43ffb521d1025e32e0eb", "point_uuid": "16", "nonfixated_pixel_x": 82, "nonfixated_pixel_y": 129, "view_id": 3}, {"camera_uuid": "57ed0722da4246b593ad7c4c816002a1", "point_uuid": "16", "nonfixated_pixel_x": 139, "nonfixated_pixel_y": 168, "view_id": 4}, {"camera_uuid": "1eea2dc63a804bb98c4433aaf5355d4d", "point_uuid": "16", "nonfixated_pixel_x": 218, "nonfixated_pixel_y": 213, "view_id": 5}, {"camera_uuid": "4c0d1c450c3c414c8e903e49190ad5f3", "point_uuid": "16", "nonfixated_pixel_x": 204, "nonfixated_pixel_y": 205, "view_id": 7}, {"camera_uuid": "b2b91e26cb9a4190a097925afea72a8a", "point_uuid": "16", "nonfixated_pixel_x": 221, "nonfixated_pixel_y": 203, "view_id": 8}, {"camera_uuid": "b20b2b0634e241d794127bb70d0381ec", "point_uuid": "16", "nonfixated_pixel_x": 215, "nonfixated_pixel_y": 139, "view_id": 9}, {"camera_uuid": "b2b91e26cb9a4190a097925afea72a8a", "point_uuid": "17", "nonfixated_pixel_x": 327, "nonfixated_pixel_y": 334, "view_id": 0}, {"camera_uuid": "4c0d1c450c3c414c8e903e49190ad5f3", "point_uuid": "17", "nonfixated_pixel_x": 168, "nonfixated_pixel_y": 321, "view_id": 2}, {"camera_uuid": "1eea2dc63a804bb98c4433aaf5355d4d", "point_uuid": "17", "nonfixated_pixel_x": 236, "nonfixated_pixel_y": 300, "view_id": 4}, {"camera_uuid": "4c0d1c450c3c414c8e903e49190ad5f3", "point_uuid": "18", "nonfixated_pixel_x": 278, "nonfixated_pixel_y": 257, "view_id": 1}, {"camera_uuid": "029e8bd017804e6aba4c5206f049bf52", "point_uuid": "18", "nonfixated_pixel_x": 468, "nonfixated_pixel_y": 306, "view_id": 2}, {"camera_uuid": "1eea2dc63a804bb98c4433aaf5355d4d", "point_uuid": "18", "nonfixated_pixel_x": 303, "nonfixated_pixel_y": 250, "view_id": 4}, {"camera_uuid": "b2b91e26cb9a4190a097925afea72a8a", "point_uuid": "18", "nonfixated_pixel_x": 391, "nonfixated_pixel_y": 250, "view_id": 6}, {"camera_uuid": "1eea2dc63a804bb98c4433aaf5355d4d", "point_uuid": "22", "nonfixated_pixel_x": 75, "nonfixated_pixel_y": 106, "view_id": 0}, {"camera_uuid": "1eea2dc63a804bb98c4433aaf5355d4d", "point_uuid": "35", "nonfixated_pixel_x": 401, "nonfixated_pixel_y": 191, "view_id": 0}, {"camera_uuid": "4c0d1c450c3c414c8e903e49190ad5f3", "point_uuid": "35", "nonfixated_pixel_x": 433, "nonfixated_pixel_y": 175, "view_id": 2}, {"camera_uuid": "1eea2dc63a804bb98c4433aaf5355d4d", "point_uuid": "38", "nonfixated_pixel_x": 488, "nonfixated_pixel_y": 259, "view_id": 5}, {"camera_uuid": "b2b91e26cb9a4190a097925afea72a8a", "point_uuid": "39", "nonfixated_pixel_x": 228, "nonfixated_pixel_y": 70, "view_id": 0}, {"camera_uuid": "4c0d1c450c3c414c8e903e49190ad5f3", "point_uuid": "39", "nonfixated_pixel_x": 159, "nonfixated_pixel_y": 91, "view_id": 2}, {"camera_uuid": "1eea2dc63a804bb98c4433aaf5355d4d", "point_uuid": "39", "nonfixated_pixel_x": 201, "nonfixated_pixel_y": 124, "view_id": 3}, {"camera_uuid": "57ed0722da4246b593ad7c4c816002a1", "point_uuid": "40", "nonfixated_pixel_x": 15, "nonfixated_pixel_y": 142, "view_id": 3}, {"camera_uuid": "1eea2dc63a804bb98c4433aaf5355d4d", "point_uuid": "48", "nonfixated_pixel_x": 274, "nonfixated_pixel_y": 185, "view_id": 0}, {"camera_uuid": "4c0d1c450c3c414c8e903e49190ad5f3", "point_uuid": "48", "nonfixated_pixel_x": 255, "nonfixated_pixel_y": 167, "view_id": 2}, {"camera_uuid": "029e8bd017804e6aba4c5206f049bf52", "point_uuid": "48", "nonfixated_pixel_x": 309, "nonfixated_pixel_y": 82, "view_id": 4}, {"camera_uuid": "b2b91e26cb9a4190a097925afea72a8a", "point_uuid": "48", "nonfixated_pixel_x": 324, "nonfixated_pixel_y": 164, "view_id": 8}, {"camera_uuid": "4c0d1c450c3c414c8e903e49190ad5f3", "point_uuid": "51", "nonfixated_pixel_x": 384, "nonfixated_pixel_y": 249, "view_id": 2}, {"camera_uuid": "1eea2dc63a804bb98c4433aaf5355d4d", "point_uuid": "51", "nonfixated_pixel_x": 374, "nonfixated_pixel_y": 245, "view_id": 3}, {"camera_uuid": "4c0d1c450c3c414c8e903e49190ad5f3", "point_uuid": "53", "nonfixated_pixel_x": 205, "nonfixated_pixel_y": 162, "view_id": 0}, {"camera_uuid": "b2b91e26cb9a4190a097925afea72a8a", "point_uuid": "53", "nonfixated_pixel_x": 266, "nonfixated_pixel_y": 156, "view_id": 2}, {"camera_uuid": "1eea2dc63a804bb98c4433aaf5355d4d", "point_uuid": "53", "nonfixated_pixel_x": 233, "nonfixated_pixel_y": 180, "view_id": 3}, {"camera_uuid": "1eea2dc63a804bb98c4433aaf5355d4d", "point_uuid": "56", "nonfixated_pixel_x": 282, "nonfixated_pixel_y": 232, "view_id": 0}, {"camera_uuid": "029e8bd017804e6aba4c5206f049bf52", "point_uuid": "56", "nonfixated_pixel_x": 303, "nonfixated_pixel_y": 214, "view_id": 1}, {"camera_uuid": "b20b2b0634e241d794127bb70d0381ec", "point_uuid": "56", "nonfixated_pixel_x": 313, "nonfixated_pixel_y": 195, "view_id": 3}, {"camera_uuid": "b2b91e26cb9a4190a097925afea72a8a", "point_uuid": "56", "nonfixated_pixel_x": 288, "nonfixated_pixel_y": 227, "view_id": 4}, {"camera_uuid": "4c0d1c450c3c414c8e903e49190ad5f3", "point_uuid": "72", "nonfixated_pixel_x": 227, "nonfixated_pixel_y": 72, "view_id": 0}, {"camera_uuid": "1eea2dc63a804bb98c4433aaf5355d4d", "point_uuid": "72", "nonfixated_pixel_x": 260, "nonfixated_pixel_y": 115, "view_id": 1}, {"camera_uuid": "b2b91e26cb9a4190a097925afea72a8a", "point_uuid": "72", "nonfixated_pixel_x": 326, "nonfixated_pixel_y": 63, "view_id": 2}, {"camera_uuid": "1eea2dc63a804bb98c4433aaf5355d4d", "point_uuid": "73", "nonfixated_pixel_x": 257, "nonfixated_pixel_y": 131, "view_id": 0}, {"camera_uuid": "b2b91e26cb9a4190a097925afea72a8a", "point_uuid": "73", "nonfixated_pixel_x": 314, "nonfixated_pixel_y": 86, "view_id": 1}, {"camera_uuid": "4c0d1c450c3c414c8e903e49190ad5f3", "point_uuid": "73", "nonfixated_pixel_x": 226, "nonfixated_pixel_y": 94, "view_id": 2}, {"camera_uuid": "029e8bd017804e6aba4c5206f049bf52", "point_uuid": "74", "nonfixated_pixel_x": 388, "nonfixated_pixel_y": 311, "view_id": 0}, {"camera_uuid": "b2b91e26cb9a4190a097925afea72a8a", "point_uuid": "74", "nonfixated_pixel_x": 353, "nonfixated_pixel_y": 277, "view_id": 4}, {"camera_uuid": "4941e1733c7d43ffb521d1025e32e0eb", "point_uuid": "75", "nonfixated_pixel_x": 60, "nonfixated_pixel_y": 250, "view_id": 1}, {"camera_uuid": "b2b91e26cb9a4190a097925afea72a8a", "point_uuid": "75", "nonfixated_pixel_x": 214, "nonfixated_pixel_y": 271, "view_id": 2}, {"camera_uuid": "57ed0722da4246b593ad7c4c816002a1", "point_uuid": "75", "nonfixated_pixel_x": 119, "nonfixated_pixel_y": 256, "view_id": 3}, {"camera_uuid": "1eea2dc63a804bb98c4433aaf5355d4d", "point_uuid": "75", "nonfixated_pixel_x": 211, "nonfixated_pixel_y": 266, "view_id": 4}, {"camera_uuid": "029e8bd017804e6aba4c5206f049bf52", "point_uuid": "75", "nonfixated_pixel_x": 162, "nonfixated_pixel_y": 280, "view_id": 5}, {"camera_uuid": "4c0d1c450c3c414c8e903e49190ad5f3", "point_uuid": "75", "nonfixated_pixel_x": 194, "nonfixated_pixel_y": 267, "view_id": 6}, {"camera_uuid": "1eea2dc63a804bb98c4433aaf5355d4d", "point_uuid": "79", "nonfixated_pixel_x": 428, "nonfixated_pixel_y": 345, "view_id": 3}, {"camera_uuid": "4c0d1c450c3c414c8e903e49190ad5f3", "point_uuid": "83", "nonfixated_pixel_x": 245, "nonfixated_pixel_y": 150, "view_id": 1}, {"camera_uuid": "1eea2dc63a804bb98c4433aaf5355d4d", "point_uuid": "83", "nonfixated_pixel_x": 269, "nonfixated_pixel_y": 172, "view_id": 2}, {"camera_uuid": "b2b91e26cb9a4190a097925afea72a8a", "point_uuid": "83", "nonfixated_pixel_x": 324, "nonfixated_pixel_y": 146, "view_id": 3}, {"camera_uuid": "b2b91e26cb9a4190a097925afea72a8a", "point_uuid": "84", "nonfixated_pixel_x": 336, "nonfixated_pixel_y": 190, "view_id": 1}, {"camera_uuid": "029e8bd017804e6aba4c5206f049bf52", "point_uuid": "84", "nonfixated_pixel_x": 336, "nonfixated_pixel_y": 142, "view_id": 5}, {"camera_uuid": "1eea2dc63a804bb98c4433aaf5355d4d", "point_uuid": "84", "nonfixated_pixel_x": 284, "nonfixated_pixel_y": 203, "view_id": 7}, {"camera_uuid": "b2b91e26cb9a4190a097925afea72a8a", "point_uuid": "85", "nonfixated_pixel_x": 343, "nonfixated_pixel_y": 257, "view_id": 0}, {"camera_uuid": "029e8bd017804e6aba4c5206f049bf52", "point_uuid": "85", "nonfixated_pixel_x": 383, "nonfixated_pixel_y": 261, "view_id": 2}, {"camera_uuid": "b20b2b0634e241d794127bb70d0381ec", "point_uuid": "85", "nonfixated_pixel_x": 435, "nonfixated_pixel_y": 239, "view_id": 3}, {"camera_uuid": "1eea2dc63a804bb98c4433aaf5355d4d", "point_uuid": "86", "nonfixated_pixel_x": 451, "nonfixated_pixel_y": 263, "view_id": 5}, {"camera_uuid": "4c0d1c450c3c414c8e903e49190ad5f3", "point_uuid": "86", "nonfixated_pixel_x": 502, "nonfixated_pixel_y": 267, "view_id": 6}, {"camera_uuid": "b2b91e26cb9a4190a097925afea72a8a", "point_uuid": "89", "nonfixated_pixel_x": 476, "nonfixated_pixel_y": 115, "view_id": 0}, {"camera_uuid": "1eea2dc63a804bb98c4433aaf5355d4d", "point_uuid": "89", "nonfixated_pixel_x": 346, "nonfixated_pixel_y": 148, "view_id": 3}, {"camera_uuid": "4c0d1c450c3c414c8e903e49190ad5f3", "point_uuid": "89", "nonfixated_pixel_x": 336, "nonfixated_pixel_y": 106, "view_id": 5}, {"camera_uuid": "b2b91e26cb9a4190a097925afea72a8a", "point_uuid": "91", "nonfixated_pixel_x": 115, "nonfixated_pixel_y": 320, "view_id": 5}, {"camera_uuid": "1eea2dc63a804bb98c4433aaf5355d4d", "point_uuid": "91", "nonfixated_pixel_x": 104, "nonfixated_pixel_y": 276, "view_id": 6}, {"camera_uuid": "1eea2dc63a804bb98c4433aaf5355d4d", "point_uuid": "94", "nonfixated_pixel_x": 384, "nonfixated_pixel_y": 261, "view_id": 1}, {"camera_uuid": "4c0d1c450c3c414c8e903e49190ad5f3", "point_uuid": "94", "nonfixated_pixel_x": 410, "nonfixated_pixel_y": 265, "view_id": 3}]}